{
  "dataNews": [
    {
      "typeLayout": "coluna",
      "columns": [
        {
          "linkProd": "link imagem 3",
          "image": {
            "src": "img-3.jpg",
            "alt": "Imagem 3"
          }
        },
        {
          "linkProd": "link imagem 3",
          "image": {
            "src": "img-3.jpg",
            "alt": "Imagem 3"
          }
        }
      ],
      "spaceImg": true
    },
    {
      "typeLayout": "linha",
      "linkProd": "link imagem 2",
      "image": {
        "src": "img-2.jpg",
        "alt": "Imagem 2",
        "space": true
      }
    }

  ]
}

